bubble_env/__init__.py
bubble_env/chain.py
bubble_env/genesis.py
bubble_env/node.py
bubble_env/base/__init__.py
bubble_env/base/host.py
bubble_env/base/process.py
bubble_env/base/service.py
bubble_env/base/supervisor/__init__.py
bubble_env/base/supervisor/supervisor.conf
bubble_env/base/supervisor/supervisor.py
bubble_env/factory/__init__.py
bubble_env/factory/factory.py
bubble_env/utils/__init__.py
bubble_env/utils/executor.py
bubble_env/utils/utils.py
bubble_env/utils/key/__init__.py
bubble_env/utils/key/keytool.py
bubble_env/utils/key/bin/keytool
bubble_env/utils/key/bin/keytool.exe
bubble_env-0.1.9.dist-info/LICENSE
bubble_env-0.1.9.dist-info/METADATA
bubble_env-0.1.9.dist-info/WHEEL
bubble_env-0.1.9.dist-info/top_level.txt
bubble_env-0.1.9.dist-info/RECORD
